chartengineer/__init__.py
chartengineer/core.py
chartengineer/utils.py
chartengineer-0.1.5.dist-info/METADATA
chartengineer-0.1.5.dist-info/WHEEL
chartengineer-0.1.5.dist-info/top_level.txt
chartengineer-0.1.5.dist-info/RECORD
