Metadata-Version: 2.4
Name: chartengineer
Version: 0.1.5
Summary: Plotly and Pandas wrapper for quick and modern chart building.
Home-page:  
Author: Brandyn Hamilton
Author-email: Brandyn Hamilton <brandynham1120@gmail.com>
License: MIT
Project-URL: Homepage, https://github.com/brandynhamilton/chartengineer
Classifier: Programming Language :: Python :: 3
Classifier: License :: OSI Approved :: MIT License
Classifier: Operating System :: OS Independent
Requires-Python: >=3.7
Requires-Dist: pandas
Requires-Dist: numpy
Requires-Dist: dotenv
Requires-Dist: plotly
Requires-Dist: matplotlib
Requires-Dist: colorcet
Requires-Dist: nbformat>=4.2.0
Requires-Dist: kaleido>=0.1.0
Provides-Extra: dev
Requires-Dist: build; extra == "dev"
Requires-Dist: twine; extra == "dev"
Dynamic: author
Dynamic: home-page
Dynamic: requires-python
